{
  "head": {
    "docType": "4",
    "editorVersion": "6.5.46",
    "c_para": {
      "package": "CONN-TH_P5.00_KF301-5.0-2P",
      "pre": "U?",
      "Contributor": "LCSC",
      "link": "https://item.szlcsc.com/481499.html",
      "3DModel": "CONN-TH_P5.00_KF301-5.0-2P"
    },
    "hasIdFlag": true,
    "x": 3990.1575,
    "y": 3000,
    "utime": 1607667855,
    "uuid": "c444d117946441c3ab8b7492a6a9cd72",
    "importFlag": 0,
    "transformList": "",
    "uuid_3d": ""
  },
  "canvas": "CA~1000~1000~#000000~yes~#FFFFFF~10~1000~1000~line~0.5~mm~1~45~visible~0.5~3990.1575~3000~0~none",
  "shape": [
    "CIRCLE~3969.972~3015.067~0.118~0.2362~101~gge55~0~~",
    "CIRCLE~3980.315~3000~1.181~2.3622~100~gge53~0~~",
    "CIRCLE~4000~3000~1.181~2.3622~100~gge54~0~~",
    "SOLIDREGION~99~~M 3969.9724 2983.752 L 4013.1299 2983.752 L 4013.1299 3015.0669 L 3969.9724 3015.0669 Z~solid~gge52~~~~0",
    "TRACK~1~3~~3970.4724 2984.252 4009.8425 2984.252~gge22~0",
    "TRACK~1~3~~4009.8425 2984.252 4009.8425 3014.5669~gge25~0",
    "TRACK~1~3~~3970.4724 2984.252 3970.4724 3014.5669~gge27~0",
    "TRACK~1~3~~3970.4724 3014.5669 4009.8425 3014.5669~gge39~0",
    "TRACK~1~3~~3970.4724 2991.3364 4009.8425 2991.3364~gge41~0",
    "TRACK~1~3~~3970.4724 3007.2622 4009.8425 3007.2622~gge43~0",
    "TRACK~1~3~~4010.1575 2989.5 4012.6299 2989.5 4012.6299 2993.5969 4010.1575 2993.5969~gge48~0",
    "PAD~ELLIPSE~3980.315~3000~8.6614~8.6614~11~~1~2.7559~~0~gge5~0~~Y~0~0~0.2~3980.315,3000",
    "PAD~ELLIPSE~4000~3000~8.6614~8.6614~11~~2~2.7559~~0~gge10~0~~Y~0~0~0.2~4000,3000",
    "SVGNODE~{\"gId\":\"g1_outline\",\"nodeName\":\"g\",\"nodeType\":1,\"layerid\":\"19\",\"attrs\":{\"c_width\":\"40.9448\",\"c_height\":\"30.3149\",\"c_rotation\":\"0,0,0\",\"z\":\"-16.9291\",\"c_origin\":\"3990.9449,2999.4094\",\"uuid\":\"a8d05e9e8af049e7986087a4d96d217f\",\"c_etype\":\"outline3D\",\"id\":\"g1_outline\",\"title\":\"CONN-TH_P5.00_KF301-5.0-2P\",\"layerid\":\"19\",\"transform\":\"scale(1) translate(0, 0)\"},\"childNodes\":[{\"gId\":\"g1_outline_line0\",\"nodeName\":\"polyline\",\"nodeType\":1,\"attrs\":{\"fill\":\"none\",\"id\":\"g1_outline_line0\",\"c_shapetype\":\"line\",\"points\":\"3970.4725 2984.252 3970.4725 2988.4252 3970.4725 2988.504 3970.4725 2989.7638 3970.4725 2990.1575 3970.4725 2994.0945 3970.4725 3006.8504 3970.4725 3012.5984 3970.4725 3014.5669 3972.441 3014.5669 3976.063 3014.5669 3977.7559 3014.5669 3982.874 3014.5669 3988.189 3014.5669 3989.1732 3014.5669 3992.126 3014.5669 3997.4409 3014.5669 4002.559 3014.5669 4007.559 3014.5669 4007.874 3014.5669 4009.8425 3014.5669 4009.8425 3012.5984 4009.8425 3006.8504 4009.8425 2994.0945 4011.4173 2994.0945 4011.4173 2992.2835 4011.4173 2992.1654 4011.4173 2990.1575 4009.8425 2990.1575 4009.8425 2989.7638 4009.8425 2988.504 4009.8425 2988.4252 4009.8425 2984.252 4007.559 2984.252 4001.8897 2984.252 3999.7637 2984.252 3997.7952 2984.252 3989.1732 2984.252 3982.2047 2984.252 3980.0787 2984.252 3978.1102 2984.252 3976.063 2984.252 3970.4725 2984.252 3970.4725 2984.252\"}}]}"
  ],
  "layers": [
    "1~TopLayer~#FF0000~true~true~true~",
    "2~BottomLayer~#0000FF~true~false~true~",
    "3~TopSilkLayer~#FFCC00~true~false~true~",
    "4~BottomSilkLayer~#66CC33~true~false~true~",
    "5~TopPasteMaskLayer~#808080~true~false~true~",
    "6~BottomPasteMaskLayer~#800000~true~false~true~",
    "7~TopSolderMaskLayer~#800080~true~false~true~0.3",
    "8~BottomSolderMaskLayer~#AA00FF~true~false~true~0.3",
    "9~Ratlines~#6464FF~true~false~true~",
    "10~BoardOutLine~#FF00FF~true~false~true~",
    "11~Multi-Layer~#FFFFFF~true~false~true~0.5",
    "12~Document~#FFFFFF~true~false~true~",
    "13~TopAssembly~#33CC99~true~false~true~",
    "14~BottomAssembly~#5555FF~true~false~true~",
    "15~Mechanical~#F022F0~true~false~true~",
    "19~3DModel~#66CCFF~true~false~true~",
    "21~Inner1~#800000~false~false~false~~",
    "22~Inner2~#008000~false~false~false~~",
    "23~Inner3~#00FF00~false~false~false~~",
    "24~Inner4~#BC8E00~false~false~false~~",
    "25~Inner5~#70DBFA~false~false~false~~",
    "26~Inner6~#00CC66~false~false~false~~",
    "27~Inner7~#9966FF~false~false~false~~",
    "28~Inner8~#800080~false~false~false~~",
    "29~Inner9~#008080~false~false~false~~",
    "30~Inner10~#15935F~false~false~false~~",
    "31~Inner11~#000080~false~false~false~~",
    "32~Inner12~#00B400~false~false~false~~",
    "33~Inner13~#2E4756~false~false~false~~",
    "34~Inner14~#99842F~false~false~false~~",
    "35~Inner15~#FFFFAA~false~false~false~~",
    "36~Inner16~#99842F~false~false~false~~",
    "37~Inner17~#2E4756~false~false~false~~",
    "38~Inner18~#3535FF~false~false~false~~",
    "39~Inner19~#8000BC~false~false~false~~",
    "40~Inner20~#43AE5F~false~false~false~~",
    "41~Inner21~#C3ECCE~false~false~false~~",
    "42~Inner22~#728978~false~false~false~~",
    "43~Inner23~#39503F~false~false~false~~",
    "44~Inner24~#0C715D~false~false~false~~",
    "45~Inner25~#5A8A80~false~false~false~~",
    "46~Inner26~#2B937E~false~false~false~~",
    "47~Inner27~#23999D~false~false~false~~",
    "48~Inner28~#45B4E3~false~false~false~~",
    "49~Inner29~#215DA1~false~false~false~~",
    "50~Inner30~#4564D7~false~false~false~~",
    "51~Inner31~#6969E9~false~false~false~~",
    "52~Inner32~#9069E9~false~false~false~~",
    "99~ComponentShapeLayer~#00CCCC~true~false~true~0.4",
    "100~LeadShapeLayer~#CC9999~true~false~true~",
    "101~ComponentPolarityLayer~#66FFCC~true~false~true~",
    "Hole~Hole~#222222~false~false~true~",
    "DRCError~DRCError~#FAD609~false~false~true~"
  ],
  "objects": [
    "All~true~false",
    "Component~true~true",
    "Prefix~true~true",
    "Name~true~false",
    "Track~true~true",
    "Pad~true~true",
    "Via~true~true",
    "Hole~true~true",
    "Copper_Area~true~true",
    "Circle~true~true",
    "Arc~true~true",
    "Solid_Region~true~true",
    "Text~true~true",
    "Image~true~true",
    "Rect~true~true",
    "Dimension~true~true",
    "Protractor~true~true"
  ],
  "BBox": {
    "x": 3969.9,
    "y": 2983.8,
    "width": 43.3,
    "height": 31.4
  },
  "netColors": {}
}